helixerlite-25.5.27.dist-info/METADATA
helixerlite-25.5.27.dist-info/WHEEL
helixerlite-25.5.27.dist-info/entry_points.txt
helixerlite-25.5.27.dist-info/licenses/LICENSE
helixerlite/__init__.py
helixerlite/__main__.py
helixerlite/hdf5.py
helixerlite/helixer_model.py
helixerlite/help_formatter.py
helixerlite/helpers.py
helixerlite/hybrid_model.py
helixerlite/log.py
helixerlite/metrics.py
helixerlite/model_files/touch.empty
helixerlite/numerify.py
helixerlite/overlap.py
helixerlite/utilities.py
helixerpost/__init__.py
helixerpost/helixerpost.cpython-39-x86_64-linux-gnu.so
helixerlite-25.5.27.dist-info/RECORD
