Metadata-Version: 2.4
Name: helixerlite
Version: 25.5.27
Classifier: Development Status :: 4 - Beta
Classifier: License :: OSI Approved :: BSD License
Classifier: Programming Language :: Python
Classifier: Operating System :: Unix
Classifier: Intended Audience :: Science/Research
Classifier: Topic :: Scientific/Engineering :: Bio-Informatics
Requires-Dist: h5py
Requires-Dist: pyfastx>=2.0.0
Requires-Dist: scikit-learn
Requires-Dist: tensorflow>=2.6.2
Requires-Dist: tensorflow-addons>=0.21.0
Requires-Dist: keras<3.0.0
Requires-Dist: keras-layer-normalization
Requires-Dist: numpy
Requires-Dist: numcodecs
Requires-Dist: gfftk
Requires-Dist: pytest>=7.0.0 ; extra == 'dev'
Requires-Dist: pytest-cov>=4.0.0 ; extra == 'dev'
Requires-Dist: pytest-mock>=3.10.0 ; extra == 'dev'
Provides-Extra: dev
License-File: LICENSE
Summary: helixerlite: simplified genome annotation with Helixer
Keywords: bioinformatics,genome,annotation
Author: Tony Bolger <bolger.tony@gmail.com>, Jonathan Palmer <nextgenusfs@gmail.com>
Author-email: Jon Palmer <nextgenusfs@gmail.com>
Requires-Python: >=3.9.0
Project-URL: Homepage, https://github.com/nextgenusfs/helixerlite
Project-URL: Repository, https://github.com/nextgenusfs/helixerlite.git
